solconfig/__init__.py
solconfig/cmd.py
solconfig/config.py
solconfig/dataclasses.py
solconfig/rest_commands.py
solconfig/solconfig.py
solconfig/spec.py
solconfig/util.py
solconfig-0.1.4.dist-info/entry_points.txt
solconfig-0.1.4.dist-info/WHEEL
solconfig-0.1.4.dist-info/METADATA
solconfig-0.1.4.dist-info/RECORD
