Metadata-Version: 2.1
Name: solconfig
Version: 0.1.4
Summary: Backing Up and Restoring Solace PubSub+ Broker Configuration with SEMPv2 protocol
Home-page: https://github.com/flyisland/solconfig
Author: flyisland
Author-email: island.chen@outlook.com
Requires-Python: >=3.6,<4.0
Classifier: Programming Language :: Python :: 3
Classifier: Programming Language :: Python :: 3.6
Classifier: Programming Language :: Python :: 3.7
Classifier: Programming Language :: Python :: 3.8
Requires-Dist: click (>=7.1.2,<8.0.0)
Requires-Dist: jinja2 (>=2.11.2,<3.0.0)
Requires-Dist: requests (>=2.24.0,<3.0.0)
Project-URL: Repository, https://github.com/flyisland/solconfig
